detection_modules/__init__.py
detection_modules/functions.py
cloudfm-0.0.1.dist-info/LICENSE
cloudfm-0.0.1.dist-info/METADATA
cloudfm-0.0.1.dist-info/WHEEL
cloudfm-0.0.1.dist-info/top_level.txt
cloudfm-0.0.1.dist-info/RECORD
