Metadata-Version: 2.1
Name: cloudfm
Version: 0.0.1
Summary: An internal package to be used by the employees of CLOUDFM company
Home-page: https://github.com/XiaozhanYang/asset-on-off-time-detection
Author: Shashank Goud
Author-email: s.goud@cloudfmgroup.com
Project-URL: Bug Tracker, https://github.com/XiaozhanYang/asset-on-off-time-detection/issues
Classifier: Programming Language :: Python :: 3
Classifier: License :: OSI Approved :: MIT License
Classifier: Operating System :: OS Independent
Requires-Python: >=3.6
License-File: LICENSE
